<annotation>
	<folder>Images</folder>
	<filename>79.jpg</filename>
	<path>C:\Users\Austin\Desktop\object-detection\Images\79.jpg</path>
	<source>
		<database>Unknown</database>
	</source>
	<size>
		<width>1739</width>
		<height>1075</height>
		<depth>3</depth>
	</size>
	<segmented>0</segmented>
	<object>
		<name>frisbee</name>
		<pose>Unspecified</pose>
		<truncated>0</truncated>
		<difficult>0</difficult>
		<bndbox>
			<xmin>157</xmin>
			<ymin>568</ymin>
			<xmax>185</xmax>
			<ymax>582</ymax>
		</bndbox>
	</object>
	<object>
		<name>frisbee</name>
		<pose>Unspecified</pose>
		<truncated>0</truncated>
		<difficult>0</difficult>
		<bndbox>
			<xmin>373</xmin>
			<ymin>320</ymin>
			<xmax>390</xmax>
			<ymax>327</ymax>
		</bndbox>
	</object>
</annotation>
